docs_helper.py
docs_helper-0.0.9.dist-info/entry_points.txt
docs_helper-0.0.9.dist-info/LICENSE
docs_helper-0.0.9.dist-info/WHEEL
docs_helper-0.0.9.dist-info/METADATA
docs_helper-0.0.9.dist-info/RECORD
