Metadata-Version: 2.1
Name: docs-helper
Version: 0.0.9
Summary: Simple interactive tool to help with intersphinx
Home-page: https://github.com/viktorfreiman/docs-helper
License: MIT
Author: Viktor Freiman
Author-email: freiman.viktor@gmail.com
Requires-Python: >=3.6.2,<4.0.0
Classifier: License :: OSI Approved :: MIT License
Classifier: Programming Language :: Python :: 3
Classifier: Programming Language :: Python :: 3.10
Classifier: Programming Language :: Python :: 3.7
Classifier: Programming Language :: Python :: 3.8
Classifier: Programming Language :: Python :: 3.9
Requires-Dist: sphobjinv (>=2.1,<3.0)
Project-URL: Documentation, https://docs-helper.readthedocs.io
Project-URL: Repository, https://github.com/viktorfreiman/docs-helper
